wavephoenix/__about__.py
wavephoenix/__init__.py
wavephoenix/cli.py
wavephoenix-0.1.1.dist-info/METADATA
wavephoenix-0.1.1.dist-info/WHEEL
wavephoenix-0.1.1.dist-info/entry_points.txt
wavephoenix-0.1.1.dist-info/RECORD
