Metadata-Version: 2.4
Name: wavephoenix
Version: 0.1.1
Summary: CLI for WavePhoenix, an open-source WaveBird receiver implementation.
Author-email: James Smith <james@loopj.com>
License-Expression: MIT
Requires-Dist: bleak
Requires-Dist: tqdm
Provides-Extra: dev
Requires-Dist: types-tqdm; extra == 'dev'
